YarpTp/__init__.py
YarpTp/yarptp.py
YarpTp-0.0.4.dist-info/LICENSE.txt
YarpTp-0.0.4.dist-info/METADATA
YarpTp-0.0.4.dist-info/WHEEL
YarpTp-0.0.4.dist-info/top_level.txt
YarpTp-0.0.4.dist-info/RECORD
