Metadata-Version: 2.1
Name: YarpTp
Version: 0.0.4
Summary: YarpTp module for Raspberry Pi
Home-page: https://github.com/IngenieriaDeSistemasUTB/YarpTp
Author: Universidad Tecnológica de Bolívar
Author-email: dirsis@utb.edu.co
License: UNKNOWN
Platform: UNKNOWN
Classifier: Programming Language :: Python :: 3
Classifier: License :: OSI Approved :: MIT License
Classifier: Operating System :: POSIX :: Linux
Classifier: Development Status :: 3 - Alpha
